weatherlink_live_local/__init__.py
weatherlink_live_local-0.4.0.dist-info/METADATA
weatherlink_live_local-0.4.0.dist-info/WHEEL
weatherlink_live_local-0.4.0.dist-info/licenses/LICENSE.txt
weatherlink_live_local-0.4.0.dist-info/RECORD
