Metadata-Version: 2.4
Name: weatherlink-live-local
Version: 0.4.0
Summary: Read current weather data from Davis WeatherLink Live units + connected sensors
Project-URL: Changelog, https://github.com/lukasberbuer/weatherlink-live-local-python/blob/master/CHANGELOG.md
Project-URL: Issues, https://github.com/lukasberbuer/weatherlink-live-local-python/issues
Project-URL: Repository, https://github.com/lukasberbuer/weatherlink-live-local-python
Author-email: Lukas Berbuer <lukas.berbuer@gmail.com>
License: MIT License
License-File: LICENSE.txt
Keywords: api,davis,iot,local,smarthome,weather,weatherlink
Classifier: Development Status :: 4 - Beta
Classifier: License :: OSI Approved :: MIT License
Classifier: Operating System :: OS Independent
Classifier: Programming Language :: Python :: 3
Classifier: Programming Language :: Python :: 3.7
Classifier: Programming Language :: Python :: 3.8
Classifier: Programming Language :: Python :: 3.9
Classifier: Programming Language :: Python :: 3.10
Classifier: Programming Language :: Python :: 3.11
Classifier: Programming Language :: Python :: 3.12
Classifier: Programming Language :: Python :: 3.13
Requires-Python: >=3.7
Requires-Dist: zeroconf
Provides-Extra: dev
Requires-Dist: coverage>=5; extra == 'dev'
Requires-Dist: furo; extra == 'dev'
Requires-Dist: hatch; extra == 'dev'
Requires-Dist: httpretty; extra == 'dev'
Requires-Dist: mypy>=0.9; extra == 'dev'
Requires-Dist: myst-parser; extra == 'dev'
Requires-Dist: pytest>=6; extra == 'dev'
Requires-Dist: ruff>=0.5; extra == 'dev'
Requires-Dist: sphinx-autodoc-typehints; extra == 'dev'
Requires-Dist: sphinx>=5; extra == 'dev'
Provides-Extra: docs
Requires-Dist: furo; extra == 'docs'
Requires-Dist: myst-parser; extra == 'docs'
Requires-Dist: sphinx-autodoc-typehints; extra == 'docs'
Requires-Dist: sphinx>=5; extra == 'docs'
Provides-Extra: tests
Requires-Dist: coverage>=5; extra == 'tests'
Requires-Dist: httpretty; extra == 'tests'
Requires-Dist: pytest>=6; extra == 'tests'
Provides-Extra: tools
Requires-Dist: hatch; extra == 'tools'
Requires-Dist: mypy>=0.9; extra == 'tools'
Requires-Dist: ruff>=0.5; extra == 'tools'
